expections.py
expections-0.2.7.dist-info/METADATA
expections-0.2.7.dist-info/WHEEL
expections-0.2.7.dist-info/top_level.txt
expections-0.2.7.dist-info/RECORD
