Metadata-Version: 2.4
Name: expections
Version: 0.2.7
Summary: A simple module that can make custom expections in specific commands.
Home-page: https://pypi.org/project/expections/
Author: wirnty
Author-email: skedovichusjdj@gmail.com
Classifier: Programming Language :: Python :: 3
Classifier: License :: OSI Approved :: MIT License
Classifier: Operating System :: OS Independent
Requires-Python: >=3.9
Dynamic: author
Dynamic: author-email
Dynamic: classifier
Dynamic: home-page
Dynamic: requires-python
Dynamic: summary
